{
    "payday": "Payday 2",
    "e:d": "Elite: Dangerous",
    "rocketleague": "Rocket League",
    "minecraft": "Minecraft",
    "spaceeng": "Space Engineers",
    "dow": "Dawn Of War Soulstorm",
    "masseffect": "Mass Effect",
    "gtav": "Grand Theft Auto V",
    "hots": "Heroes of the Storm",
    "showdown": "Pokemon Showdown",
    "overwatch": "Overwatch",
    "rotr": "Rise of the Reds. Kappa.",
    "lol": "League of Legends",
    "starbound": "Starbound",
    "insurgency": "Insurgency",
    "diablo": "Diablo",
    "test": "Test",
    "triforce": "Triforce Heroes",
    "csgo": "CS:GO",
    "ttt": "Trouble in Terrorist Town",
    "sc2": "Starcraft 2",
    "contagion": "Contagion",
    "civ": "Civilization V",
    "tabletop": "Tabletop Simulator",
    "borderlands": "Borderlands 2",
    "halo": "Halo Online"
}